<?xml version="1.0" encoding="utf-8"?>
<!DOCTYPE hibernate-mapping PUBLIC "-//Hibernate/Hibernate Mapping DTD 3.0//EN"
"http://www.hibernate.org/dtd/hibernate-mapping-3.0.dtd">
<!-- 
    Mapping file autogenerated by MyEclipse Persistence Tools
-->
<hibernate-mapping>
    <class name="com.clinic.admin.model.impl.ServiceMaster" table="SERVICE" >
        <id name="id" type="java.lang.Long">
            <column name="ID"  />
            <generator class="identity" />
        </id>
       
        <property name="code" type="java.lang.String">
            <column name="CODE" length="50" not-null="true" />
        </property>
        
        <property name="name" type="java.lang.String">
            <column name="NAME" length="200" not-null="true" />
        </property>
        
        
        <property name="typeCode" type="java.lang.String">
            <column name="TYPECODE" length="50" not-null="true" />
        </property>
        
        <property name="groupCode" type="java.lang.String">
            <column name="GROUPCODE" length="50" not-null="true" />
        </property>
        
        <property name="visitType" type="java.lang.String">
            <column name="VISITTYPE" length="50" not-null="true" />
        </property>
        
        <property name="specialInstructions" type="java.lang.String">
            <column name="SPECIALINSTRUCTIONS" length="1000" not-null="true" />
        </property>
        
        <property name="sellingPrice" type="java.math.BigDecimal">
            <column name="SELLINGPRICE" length="50" not-null="true" />
        </property>
        
        <property name="estimationTimeMins" type="java.math.BigDecimal">
            <column name="ESTIMATIONTIMEMINS" length="200" not-null="true" />
        </property>
        
        <property name="cptCode" type="java.lang.String">
            <column name="CPTCODE" length="50" not-null="true" />
        </property>
        
        <property name="activityType" type="java.lang.String">
            <column name="ACTIVITYTYPE" length="400" not-null="true" />
        </property>
        
        
         <property name="isAppointableDummy" type="java.lang.Short">
            <column name="ISAPPOINTABLE" length="50" not-null="true" />
        </property>
         <property name="isMultipleDummy" type="java.lang.Short">
            <column name="ISMULTIPLE" length="50" not-null="true" />
        </property>
         <property name="isChargableDummy" type="java.lang.Short">
            <column name="ISCHARGABLE" length="50" not-null="true" />
        </property>
         <property name="isResourceDependentDummy" type="java.lang.Short">
            <column name="ISRESOURCEDEPENDENT" length="50" not-null="true" />
        </property>
         <property name="isPackageServiceDummy" type="java.lang.Short">
            <column name="ISPACKAGESERVICE" length="50" not-null="true" />
        </property>
         <property name="isSurgicalServiceDummy" type="java.lang.Short">
            <column name="ISSURGICALSERVICE" length="50" not-null="true" />
        </property>
         <property name="isEquipmentRequiredDummy" type="java.lang.Short">
            <column name="ISEQUIPMENTREQUIRED" length="50" not-null="true" />
        </property>
         <property name="isOTRequiredDummy" type="java.lang.Short">
            <column name="ISOTREQUIRED" length="50" not-null="true" />
        </property>
         <property name="isHighRatedDummy" type="java.lang.Short">
            <column name="ISHIGHRATED" length="50" not-null="true" />
        </property>
        <property name="isAuthorisationRequiredDummy" type="java.lang.Short">
            <column name="ISAUTHORISATIONREQUIRED" length="50" not-null="true" />
        </property>
        
        <property name="isActiveDummy" type="java.lang.Short">
            <column name="ISACTIVE" length="50" not-null="true" />
        </property>
        <property name="createdBy" type="java.lang.String">
            <column name="CREATEDBY" />
        </property>
        
        <property name="createdTime" type="timestamp">
            <column name="CREATEDTIME" />
        </property>
        <property name="updatedTime" type="timestamp">
            <column name="UPDATEDTIME" />
        </property>
         <property name="updatedBy" type="java.lang.String">
            <column name="UPDATEDBY" />
        </property>
      </class>
</hibernate-mapping>
